devtools_word_counter/__init__.py
devtools_word_counter-1.0.1.dist-info/METADATA
devtools_word_counter-1.0.1.dist-info/WHEEL
devtools_word_counter-1.0.1.dist-info/top_level.txt
devtools_word_counter-1.0.1.dist-info/RECORD
