Metadata-Version: 2.1
Name: devtools-word-counter
Version: 1.0.1
Summary: Word and character counter
Home-page: https://devtools.at/tools/word-counter
Author: DevTools.at
Author-email: hello@devtools.at
Project-URL: Homepage, https://devtools.at/tools/word-counter
Project-URL: Repository, https://github.com/devtools-at/word-counter
Classifier: Development Status :: 4 - Beta
Classifier: Intended Audience :: Developers
Classifier: License :: OSI Approved :: MIT License
Classifier: Programming Language :: Python :: 3
Requires-Python: >=3.8
